{"tile_size": 16, "tilemap": {"4;10": {"kind": "stone", "pos": [4.0, 10.0], "variant": 8}, "5;10": {"kind": "stone", "pos": [5.0, 10.0], "variant": 1}, "6;10": {"kind": "stone", "pos": [6.0, 10.0], "variant": 1}, "7;10": {"kind": "stone", "pos": [7.0, 10.0], "variant": 1}, "8;10": {"kind": "stone", "pos": [8.0, 10.0], "variant": 8}, "9;10": {"kind": "stone", "pos": [9.0, 10.0], "variant": 8}, "10;10": {"kind": "stone", "pos": [10.0, 10.0], "variant": 8}, "11;10": {"kind": "stone", "pos": [11.0, 10.0], "variant": 8}, "13;11": {"kind": "stone", "pos": [13.0, 11.0], "variant": 8}, "12;11": {"kind": "stone", "pos": [12.0, 11.0], "variant": 8}, "11;11": {"kind": "stone", "pos": [11.0, 11.0], "variant": 8}, "10;11": {"kind": "stone", "pos": [10.0, 11.0], "variant": 8}, "9;11": {"kind": "stone", "pos": [9.0, 11.0], "variant": 8}, "8;11": {"kind": "stone", "pos": [8.0, 11.0], "variant": 8}, "7;11": {"kind": "stone", "pos": [7.0, 11.0], "variant": 8}, "6;11": {"kind": "stone", "pos": [6.0, 11.0], "variant": 8}, "5;11": {"kind": "stone", "pos": [5.0, 11.0], "variant": 8}, "4;11": {"kind": "stone", "pos": [4.0, 11.0], "variant": 8}, "4;12": {"kind": "stone", "pos": [4.0, 12.0], "variant": 5}, "5;12": {"kind": "stone", "pos": [5.0, 12.0], "variant": 5}, "6;12": {"kind": "stone", "pos": [6.0, 12.0], "variant": 5}, "7;12": {"kind": "stone", "pos": [7.0, 12.0], "variant": 5}, "8;12": {"kind": "stone", "pos": [8.0, 12.0], "variant": 5}, "9;12": {"kind": "stone", "pos": [9.0, 12.0], "variant": 5}, "10;12": {"kind": "stone", "pos": [10.0, 12.0], "variant": 5}, "11;12": {"kind": "stone", "pos": [11.0, 12.0], "variant": 5}, "12;12": {"kind": "stone", "pos": [12.0, 12.0], "variant": 5}, "13;12": {"kind": "stone", "pos": [13.0, 12.0], "variant": 5}, "12;10": {"kind": "stone", "pos": [12.0, 10.0], "variant": 8}, "13;10": {"kind": "stone", "pos": [13.0, 10.0], "variant": 8}, "14;10": {"kind": "stone", "pos": [14.0, 10.0], "variant": 8}, "15;10": {"kind": "stone", "pos": [15.0, 10.0], "variant": 8}, "16;10": {"kind": "stone", "pos": [16.0, 10.0], "variant": 8}, "17;10": {"kind": "stone", "pos": [17.0, 10.0], "variant": 8}, "18;10": {"kind": "stone", "pos": [18.0, 10.0], "variant": 8}, "19;10": {"kind": "stone", "pos": [19.0, 10.0], "variant": 8}, "19;11": {"kind": "stone", "pos": [19.0, 11.0], "variant": 8}, "19;12": {"kind": "stone", "pos": [19.0, 12.0], "variant": 5}, "18;12": {"kind": "stone", "pos": [18.0, 12.0], "variant": 5}, "17;12": {"kind": "stone", "pos": [17.0, 12.0], "variant": 5}, "16;12": {"kind": "stone", "pos": [16.0, 12.0], "variant": 5}, "15;12": {"kind": "stone", "pos": [15.0, 12.0], "variant": 5}, "14;11": {"kind": "stone", "pos": [14.0, 11.0], "variant": 8}, "15;11": {"kind": "stone", "pos": [15.0, 11.0], "variant": 8}, "16;11": {"kind": "stone", "pos": [16.0, 11.0], "variant": 8}, "17;11": {"kind": "stone", "pos": [17.0, 11.0], "variant": 8}, "18;11": {"kind": "stone", "pos": [18.0, 11.0], "variant": 8}, "20;10": {"kind": "stone", "pos": [20.0, 10.0], "variant": 8}, "21;10": {"kind": "stone", "pos": [21.0, 10.0], "variant": 8}, "21;11": {"kind": "stone", "pos": [21.0, 11.0], "variant": 8}, "21;12": {"kind": "stone", "pos": [21.0, 12.0], "variant": 5}, "20;12": {"kind": "stone", "pos": [20.0, 12.0], "variant": 5}, "20;11": {"kind": "stone", "pos": [20.0, 11.0], "variant": 8}, "24;11": {"kind": "stone", "pos": [24.0, 11.0], "variant": 8}, "24;12": {"kind": "stone", "pos": [24.0, 12.0], "variant": 5}, "23;12": {"kind": "stone", "pos": [23.0, 12.0], "variant": 5}, "22;12": {"kind": "stone", "pos": [22.0, 12.0], "variant": 5}, "22;11": {"kind": "stone", "pos": [22.0, 11.0], "variant": 8}, "22;10": {"kind": "stone", "pos": [22.0, 10.0], "variant": 8}, "23;10": {"kind": "stone", "pos": [23.0, 10.0], "variant": 8}, "23;11": {"kind": "stone", "pos": [23.0, 11.0], "variant": 8}, "24;10": {"kind": "stone", "pos": [24.0, 10.0], "variant": 8}, "25;10": {"kind": "stone", "pos": [25.0, 10.0], "variant": 8}, "25;11": {"kind": "stone", "pos": [25.0, 11.0], "variant": 8}, "25;12": {"kind": "stone", "pos": [25.0, 12.0], "variant": 5}, "3;10": {"kind": "stone", "pos": [3.0, 10.0], "variant": 7}, "3;11": {"kind": "stone", "pos": [3.0, 11.0], "variant": 7}, "3;12": {"kind": "stone", "pos": [3.0, 12.0], "variant": 6}, "26;10": {"kind": "stone", "pos": [26.0, 10.0], "variant": 8}, "26;11": {"kind": "stone", "pos": [26.0, 11.0], "variant": 8}, "26;12": {"kind": "stone", "pos": [26.0, 12.0], "variant": 5}, "27;12": {"kind": "stone", "pos": [27.0, 12.0], "variant": 5}, "27;11": {"kind": "stone", "pos": [27.0, 11.0], "variant": 8}, "27;10": {"kind": "stone", "pos": [27.0, 10.0], "variant": 8}, "28;10": {"kind": "stone", "pos": [28.0, 10.0], "variant": 8}, "28;11": {"kind": "stone", "pos": [28.0, 11.0], "variant": 8}, "28;12": {"kind": "stone", "pos": [28.0, 12.0], "variant": 5}, "14;12": {"kind": "stone", "pos": [14.0, 12.0], "variant": 5}, "23;7": {"kind": "granite", "pos": [23.0, 7.0], "variant": 0}, "24;7": {"kind": "granite", "pos": [24.0, 7.0], "variant": 0}, "25;7": {"kind": "granite", "pos": [25.0, 7.0], "variant": 0}, "26;7": {"kind": "granite", "pos": [26.0, 7.0], "variant": 0}, "27;7": {"kind": "granite", "pos": [27.0, 7.0], "variant": 0}, "25;9": {"kind": "stone", "pos": [25.0, 9.0], "variant": 1}, "24;9": {"kind": "stone", "pos": [24.0, 9.0], "variant": 1}, "23;9": {"kind": "stone", "pos": [23.0, 9.0], "variant": 1}, "22;9": {"kind": "stone", "pos": [22.0, 9.0], "variant": 1}, "21;9": {"kind": "stone", "pos": [21.0, 9.0], "variant": 1}, "20;9": {"kind": "stone", "pos": [20.0, 9.0], "variant": 1}, "19;9": {"kind": "stone", "pos": [19.0, 9.0], "variant": 1}, "18;9": {"kind": "stone", "pos": [18.0, 9.0], "variant": 1}, "17;9": {"kind": "stone", "pos": [17.0, 9.0], "variant": 1}, "16;9": {"kind": "stone", "pos": [16.0, 9.0], "variant": 1}, "15;9": {"kind": "stone", "pos": [15.0, 9.0], "variant": 1}, "14;9": {"kind": "stone", "pos": [14.0, 9.0], "variant": 1}, "13;9": {"kind": "stone", "pos": [13.0, 9.0], "variant": 1}, "23;3": {"kind": "granite", "pos": [23.0, 3.0], "variant": 0}, "24;3": {"kind": "granite", "pos": [24.0, 3.0], "variant": 0}, "3;9": {"kind": "stone", "pos": [3.0, 9.0], "variant": 7}, "3;8": {"kind": "stone", "pos": [3.0, 8.0], "variant": 7}, "3;7": {"kind": "stone", "pos": [3.0, 7.0], "variant": 7}, "3;6": {"kind": "stone", "pos": [3.0, 6.0], "variant": 7}, "3;5": {"kind": "stone", "pos": [3.0, 5.0], "variant": 7}, "3;4": {"kind": "stone", "pos": [3.0, 4.0], "variant": 7}, "3;3": {"kind": "stone", "pos": [3.0, 3.0], "variant": 7}, "3;2": {"kind": "stone", "pos": [3.0, 2.0], "variant": 7}, "3;1": {"kind": "stone", "pos": [3.0, 1.0], "variant": 7}, "3;0": {"kind": "stone", "pos": [3.0, 0.0], "variant": 7}, "3;-1": {"kind": "stone", "pos": [3.0, -1.0], "variant": 7}, "3;-2": {"kind": "stone", "pos": [3.0, -2.0], "variant": 7}, "3;-3": {"kind": "stone", "pos": [3.0, -3.0], "variant": 7}, "3;-4": {"kind": "stone", "pos": [3.0, -4.0], "variant": 7}, "3;-5": {"kind": "stone", "pos": [3.0, -5.0], "variant": 7}, "3;-6": {"kind": "stone", "pos": [3.0, -6.0], "variant": 7}, "3;-7": {"kind": "stone", "pos": [3.0, -7.0], "variant": 0}, "4;-7": {"kind": "stone", "pos": [4.0, -7.0], "variant": 1}, "5;-7": {"kind": "stone", "pos": [5.0, -7.0], "variant": 1}, "6;-7": {"kind": "stone", "pos": [6.0, -7.0], "variant": 1}, "7;-7": {"kind": "stone", "pos": [7.0, -7.0], "variant": 1}, "8;-7": {"kind": "stone", "pos": [8.0, -7.0], "variant": 1}, "9;-7": {"kind": "stone", "pos": [9.0, -7.0], "variant": 1}, "10;-7": {"kind": "stone", "pos": [10.0, -7.0], "variant": 1}, "11;-7": {"kind": "stone", "pos": [11.0, -7.0], "variant": 1}, "14;-7": {"kind": "stone", "pos": [14.0, -7.0], "variant": 1}, "13;-7": {"kind": "stone", "pos": [13.0, -7.0], "variant": 1}, "12;-7": {"kind": "stone", "pos": [12.0, -7.0], "variant": 1}, "15;-7": {"kind": "stone", "pos": [15.0, -7.0], "variant": 1}, "16;-7": {"kind": "stone", "pos": [16.0, -7.0], "variant": 1}, "17;-7": {"kind": "stone", "pos": [17.0, -7.0], "variant": 1}, "18;-7": {"kind": "stone", "pos": [18.0, -7.0], "variant": 1}, "19;-7": {"kind": "stone", "pos": [19.0, -7.0], "variant": 1}, "20;-7": {"kind": "stone", "pos": [20.0, -7.0], "variant": 1}, "21;-7": {"kind": "stone", "pos": [21.0, -7.0], "variant": 1}, "22;-7": {"kind": "stone", "pos": [22.0, -7.0], "variant": 1}, "23;-7": {"kind": "stone", "pos": [23.0, -7.0], "variant": 1}, "27;-7": {"kind": "stone", "pos": [27.0, -7.0], "variant": 1}, "28;-7": {"kind": "stone", "pos": [28.0, -7.0], "variant": 1}, "29;-7": {"kind": "stone", "pos": [29.0, -7.0], "variant": 1}, "30;-7": {"kind": "stone", "pos": [30.0, -7.0], "variant": 1}, "31;-7": {"kind": "stone", "pos": [31.0, -7.0], "variant": 1}, "32;-7": {"kind": "stone", "pos": [32.0, -7.0], "variant": 2}, "32;-6": {"kind": "stone", "pos": [32.0, -6.0], "variant": 3}, "32;-5": {"kind": "stone", "pos": [32.0, -5.0], "variant": 3}, "32;-4": {"kind": "stone", "pos": [32.0, -4.0], "variant": 3}, "32;-3": {"kind": "stone", "pos": [32.0, -3.0], "variant": 3}, "32;-2": {"kind": "stone", "pos": [32.0, -2.0], "variant": 3}, "32;-1": {"kind": "stone", "pos": [32.0, -1.0], "variant": 3}, "32;3": {"kind": "stone", "pos": [32.0, 3.0], "variant": 3}, "32;4": {"kind": "stone", "pos": [32.0, 4.0], "variant": 3}, "32;5": {"kind": "stone", "pos": [32.0, 5.0], "variant": 3}, "32;6": {"kind": "stone", "pos": [32.0, 6.0], "variant": 3}, "32;7": {"kind": "stone", "pos": [32.0, 7.0], "variant": 3}, "32;8": {"kind": "stone", "pos": [32.0, 8.0], "variant": 3}, "32;9": {"kind": "stone", "pos": [32.0, 9.0], "variant": 3}, "32;10": {"kind": "stone", "pos": [32.0, 10.0], "variant": 3}, "32;11": {"kind": "stone", "pos": [32.0, 11.0], "variant": 3}, "32;12": {"kind": "stone", "pos": [32.0, 12.0], "variant": 4}, "31;12": {"kind": "stone", "pos": [31.0, 12.0], "variant": 5}, "30;12": {"kind": "stone", "pos": [30.0, 12.0], "variant": 5}, "29;12": {"kind": "stone", "pos": [29.0, 12.0], "variant": 5}, "32;2": {"kind": "stone", "pos": [32.0, 2.0], "variant": 3}, "32;1": {"kind": "stone", "pos": [32.0, 1.0], "variant": 3}, "32;0": {"kind": "stone", "pos": [32.0, 0.0], "variant": 3}, "26;-7": {"kind": "stone", "pos": [26.0, -7.0], "variant": 1}, "25;-7": {"kind": "stone", "pos": [25.0, -7.0], "variant": 1}, "24;-7": {"kind": "stone", "pos": [24.0, -7.0], "variant": 1}, "4;2": {"kind": "stone", "pos": [4.0, 2.0], "variant": 3}, "4;7": {"kind": "stone", "pos": [4.0, 7.0], "variant": 3}, "29;11": {"kind": "stone", "pos": [29.0, 11.0], "variant": 8}, "30;11": {"kind": "stone", "pos": [30.0, 11.0], "variant": 8}, "31;11": {"kind": "stone", "pos": [31.0, 11.0], "variant": 8}, "31;10": {"kind": "stone", "pos": [31.0, 10.0], "variant": 8}, "31;9": {"kind": "stone", "pos": [31.0, 9.0], "variant": 8}, "31;8": {"kind": "stone", "pos": [31.0, 8.0], "variant": 7}, "31;7": {"kind": "stone", "pos": [31.0, 7.0], "variant": 7}, "31;6": {"kind": "stone", "pos": [31.0, 6.0], "variant": 7}, "31;5": {"kind": "stone", "pos": [31.0, 5.0], "variant": 7}, "31;4": {"kind": "stone", "pos": [31.0, 4.0], "variant": 7}, "31;3": {"kind": "stone", "pos": [31.0, 3.0], "variant": 7}, "31;2": {"kind": "stone", "pos": [31.0, 2.0], "variant": 7}, "31;1": {"kind": "stone", "pos": [31.0, 1.0], "variant": 7}, "31;0": {"kind": "stone", "pos": [31.0, 0.0], "variant": 7}, "31;-1": {"kind": "stone", "pos": [31.0, -1.0], "variant": 7}, "31;-2": {"kind": "stone", "pos": [31.0, -2.0], "variant": 7}, "31;-3": {"kind": "stone", "pos": [31.0, -3.0], "variant": 7}, "31;-4": {"kind": "stone", "pos": [31.0, -4.0], "variant": 7}, "31;-5": {"kind": "stone", "pos": [31.0, -5.0], "variant": 7}, "31;-6": {"kind": "stone", "pos": [31.0, -6.0], "variant": 8}, "30;-6": {"kind": "stone", "pos": [30.0, -6.0], "variant": 5}, "29;-6": {"kind": "stone", "pos": [29.0, -6.0], "variant": 5}, "28;-6": {"kind": "stone", "pos": [28.0, -6.0], "variant": 5}, "27;-6": {"kind": "stone", "pos": [27.0, -6.0], "variant": 5}, "26;-6": {"kind": "stone", "pos": [26.0, -6.0], "variant": 5}, "25;-6": {"kind": "stone", "pos": [25.0, -6.0], "variant": 5}, "24;-6": {"kind": "stone", "pos": [24.0, -6.0], "variant": 5}, "23;-6": {"kind": "stone", "pos": [23.0, -6.0], "variant": 5}, "22;-6": {"kind": "stone", "pos": [22.0, -6.0], "variant": 5}, "21;-6": {"kind": "stone", "pos": [21.0, -6.0], "variant": 5}, "20;-6": {"kind": "stone", "pos": [20.0, -6.0], "variant": 5}, "19;-6": {"kind": "stone", "pos": [19.0, -6.0], "variant": 5}, "18;-6": {"kind": "stone", "pos": [18.0, -6.0], "variant": 5}, "17;-6": {"kind": "stone", "pos": [17.0, -6.0], "variant": 5}, "16;-6": {"kind": "stone", "pos": [16.0, -6.0], "variant": 5}, "15;-6": {"kind": "stone", "pos": [15.0, -6.0], "variant": 5}, "14;-6": {"kind": "stone", "pos": [14.0, -6.0], "variant": 5}, "13;-6": {"kind": "stone", "pos": [13.0, -6.0], "variant": 5}, "12;-6": {"kind": "stone", "pos": [12.0, -6.0], "variant": 5}, "11;-6": {"kind": "stone", "pos": [11.0, -6.0], "variant": 5}, "10;-6": {"kind": "stone", "pos": [10.0, -6.0], "variant": 5}, "9;-6": {"kind": "stone", "pos": [9.0, -6.0], "variant": 5}, "8;-6": {"kind": "stone", "pos": [8.0, -6.0], "variant": 5}, "7;-6": {"kind": "stone", "pos": [7.0, -6.0], "variant": 5}, "6;-6": {"kind": "stone", "pos": [6.0, -6.0], "variant": 5}, "5;-6": {"kind": "stone", "pos": [5.0, -6.0], "variant": 5}, "4;-6": {"kind": "stone", "pos": [4.0, -6.0], "variant": 8}, "4;9": {"kind": "stone", "pos": [4.0, 9.0], "variant": 3}, "4;8": {"kind": "stone", "pos": [4.0, 8.0], "variant": 3}, "4;6": {"kind": "stone", "pos": [4.0, 6.0], "variant": 3}, "4;5": {"kind": "stone", "pos": [4.0, 5.0], "variant": 3}, "4;4": {"kind": "stone", "pos": [4.0, 4.0], "variant": 3}, "4;3": {"kind": "stone", "pos": [4.0, 3.0], "variant": 3}, "4;1": {"kind": "stone", "pos": [4.0, 1.0], "variant": 3}, "4;0": {"kind": "stone", "pos": [4.0, 0.0], "variant": 3}, "4;-1": {"kind": "stone", "pos": [4.0, -1.0], "variant": 3}, "4;-2": {"kind": "stone", "pos": [4.0, -2.0], "variant": 3}, "4;-3": {"kind": "stone", "pos": [4.0, -3.0], "variant": 3}, "4;-4": {"kind": "stone", "pos": [4.0, -4.0], "variant": 3}, "4;-5": {"kind": "stone", "pos": [4.0, -5.0], "variant": 3}, "22;3": {"kind": "granite", "pos": [22.0, 3.0], "variant": 0}, "21;3": {"kind": "granite", "pos": [21.0, 3.0], "variant": 0}, "20;3": {"kind": "granite", "pos": [20.0, 3.0], "variant": 0}, "19;3": {"kind": "granite", "pos": [19.0, 3.0], "variant": 0}, "25;3": {"kind": "granite", "pos": [25.0, 3.0], "variant": 0}, "26;3": {"kind": "granite", "pos": [26.0, 3.0], "variant": 0}, "27;3": {"kind": "granite", "pos": [27.0, 3.0], "variant": 0}, "12;-1": {"kind": "granite", "pos": [12.0, -1.0], "variant": 0}, "12;0": {"kind": "granite", "pos": [12.0, 0.0], "variant": 0}, "12;1": {"kind": "granite", "pos": [12.0, 1.0], "variant": 0}, "12;2": {"kind": "granite", "pos": [12.0, 2.0], "variant": 0}, "12;3": {"kind": "granite", "pos": [12.0, 3.0], "variant": 0}, "20;6": {"kind": "granite", "pos": [20.0, 6.0], "variant": 0}, "19;6": {"kind": "granite", "pos": [19.0, 6.0], "variant": 0}, "18;6": {"kind": "granite", "pos": [18.0, 6.0], "variant": 0}, "17;6": {"kind": "granite", "pos": [17.0, 6.0], "variant": 0}, "16;6": {"kind": "granite", "pos": [16.0, 6.0], "variant": 0}, "15;6": {"kind": "granite", "pos": [15.0, 6.0], "variant": 0}, "14;6": {"kind": "granite", "pos": [14.0, 6.0], "variant": 0}, "13;6": {"kind": "granite", "pos": [13.0, 6.0], "variant": 0}, "12;6": {"kind": "granite", "pos": [12.0, 6.0], "variant": 6}, "12;-2": {"kind": "granite", "pos": [12.0, -2.0], "variant": 1}, "13;-2": {"kind": "granite", "pos": [13.0, -2.0], "variant": 0}, "14;-2": {"kind": "granite", "pos": [14.0, -2.0], "variant": 0}, "15;-2": {"kind": "granite", "pos": [15.0, -2.0], "variant": 0}, "16;-2": {"kind": "granite", "pos": [16.0, -2.0], "variant": 0}, "17;-2": {"kind": "granite", "pos": [17.0, -2.0], "variant": 0}, "5;-2": {"kind": "granite", "pos": [5.0, -2.0], "variant": 0}, "6;-2": {"kind": "granite", "pos": [6.0, -2.0], "variant": 0}, "7;-2": {"kind": "granite", "pos": [7.0, -2.0], "variant": 0}, "8;-2": {"kind": "granite", "pos": [8.0, -2.0], "variant": 0}, "9;-2": {"kind": "granite", "pos": [9.0, -2.0], "variant": 0}, "10;-2": {"kind": "granite", "pos": [10.0, -2.0], "variant": 0}, "11;-2": {"kind": "granite", "pos": [11.0, -2.0], "variant": 0}, "5;-1": {"kind": "spike", "pos": [5.0, -1.0], "variant": 1}, "11;0": {"kind": "spike", "pos": [11.0, 0.0], "variant": 3}, "11;1": {"kind": "spike", "pos": [11.0, 1.0], "variant": 3}, "11;2": {"kind": "spike", "pos": [11.0, 2.0], "variant": 3}, "23;4": {"kind": "spike", "pos": [23.0, 4.0], "variant": 1}, "24;4": {"kind": "spike", "pos": [24.0, 4.0], "variant": 1}, "26;9": {"kind": "stone", "pos": [26.0, 9.0], "variant": 1}, "27;9": {"kind": "stone", "pos": [27.0, 9.0], "variant": 1}, "28;9": {"kind": "stone", "pos": [28.0, 9.0], "variant": 1}, "29;9": {"kind": "stone", "pos": [29.0, 9.0], "variant": 1}, "29;10": {"kind": "stone", "pos": [29.0, 10.0], "variant": 8}, "30;9": {"kind": "stone", "pos": [30.0, 9.0], "variant": 1}, "30;10": {"kind": "stone", "pos": [30.0, 10.0], "variant": 8}, "11;6": {"kind": "stone", "pos": [11.0, 6.0], "variant": 0}, "10;6": {"kind": "stone", "pos": [10.0, 6.0], "variant": 0}, "9;6": {"kind": "stone", "pos": [9.0, 6.0], "variant": 0}, "8;6": {"kind": "stone", "pos": [8.0, 6.0], "variant": 0}, "7;6": {"kind": "stone", "pos": [7.0, 6.0], "variant": 0}, "6;6": {"kind": "stone", "pos": [6.0, 6.0], "variant": 0}, "8;9": {"kind": "stone", "pos": [8.0, 9.0], "variant": 0}, "7;9": {"kind": "stone", "pos": [7.0, 9.0], "variant": 0}, "6;9": {"kind": "stone", "pos": [6.0, 9.0], "variant": 0}, "5;9": {"kind": "stone", "pos": [5.0, 9.0], "variant": 0}, "9;9": {"kind": "spike", "pos": [9.0, 9.0], "variant": 0}, "10;9": {"kind": "spike", "pos": [10.0, 9.0], "variant": 0}, "11;9": {"kind": "spike", "pos": [11.0, 9.0], "variant": 0}, "12;9": {"kind": "spike", "pos": [12.0, 9.0], "variant": 0}}, "offgrid": [{"kind": "spawners", "pos": [228.5, -48.5], "variant": 1}, {"kind": "spawners", "pos": [101.0, 78.5], "variant": 0}, {"kind": "spawners", "pos": [203.0, -48.0], "variant": 1}, {"kind": "spawners", "pos": [280.0, 128.5], "variant": 1}, {"kind": "spawners", "pos": [475.0, 122.5], "variant": 2}, {"kind": "decor", "pos": [276.0, -41.0], "variant": 2}, {"kind": "spawners", "pos": [360.5, 129.0], "variant": 1}, {"kind": "spawners", "pos": [433.5, 94.5], "variant": 1}, {"kind": "spawners", "pos": [375.0, 31.0], "variant": 1}, {"kind": "spawners", "pos": [383.0, 94.0], "variant": 1}, {"kind": "spawners", "pos": [253.5, -48.5], "variant": 1}]}